<beans xmlns="http://www.springframework.org/schema/beans"
 xmlns:xsi="http://www.w3.org/2001/XMLSchema-instance" xmlns:context="http://www.springframework.org/schema/context"
 xmlns:tx="http://www.springframework.org/schema/tx" xmlns:jpa="http://www.springframework.org/schema/data/jpa"
 xsi:schemaLocation="http://www.springframework.org/schema/beans
http://www.springframework.org/schema/beans/spring-beans-4.0.xsd
http://www.springframework.org/schema/context
http://www.springframework.org/schema/context/spring-context-4.0.xsd
http://www.springframework.org/schema/tx 
http://www.springframework.org/schema/tx/spring-tx-4.0.xsd
http://www.springframework.org/schema/data/jpa 
http://www.springframework.org/schema/data/jpa/spring-jpa.xsd
">
 <!-- Datasource bean -->
 <context:property-placeholder location="classpath:properties/dao.properties" />
 <bean id="dataSource"
  class="org.springframework.jdbc.datasource.DriverManagerDataSource">
  <property name="driverClassName" value="${driver}" />
  <property name="url" value="${url}" />
  <property name="username" value="${nomutilisateur}" />
  <property name="password" value="${motdepasse}" />
 </bean>

 <!-- Create default configuration for Hibernate -->
 <bean id="jpaVendorAdapter"
  class="org.springframework.orm.jpa.vendor.HibernateJpaVendorAdapter">
  <property name="showSql" value="true" />
  <property name="databasePlatform" value="org.hibernate.dialect.MySQLDialect" />
  <property name="generateDdl" value="true" />
  <property name="database" value="MYSQL" />
 </bean>

 <bean id="entityManagerFactory"
  class="org.springframework.orm.jpa.LocalContainerEntityManagerFactoryBean">
  <property name="dataSource" ref="dataSource" />
  <property name="jpaVendorAdapter" ref="jpaVendorAdapter" />
  <!-- spring based scanning for entity classes -->
  <property name="packagesToScan" value="com.excilys.cdb.models" />
 </bean>

 <!-- Configure the transaction manager bean -->
 <bean id="transactionManager" class="org.springframework.orm.jpa.JpaTransactionManager">
  <property name="entityManagerFactory" ref="entityManagerFactory" />
 </bean>

 <!-- Enable annotation driven transaction management -->
 <tx:annotation-driven />

 <!-- Configure Spring Data JPA and set the base package of the repository 
  interfaces -->
 <jpa:repositories base-package="com.excilys.cdb.daos.repositories" />

 <!-- Packages to scan -->
 <context:component-scan base-package="com.excilys.cdb.services" />
 <context:component-scan base-package="com.excilys.cdb.cli" />
 <context:component-scan base-package="com.excilys.cdb.daos" />
 <context:component-scan base-package="com.excilys.cdb.models" />

</beans>